pyslabs/__init__.py
pyslabs/__main__.py
pyslabs/command.py
pyslabs/const.py
pyslabs/core.py
pyslabs/error.py
pyslabs/read.py
pyslabs/slabif.py
pyslabs/slabif_builtins.py
pyslabs/slabif_numpy.py
pyslabs/util.py
pyslabs/write.py
pyslabs/old/__init__.py
pyslabs/old/__main__.py
pyslabs/old/data.py
pyslabs/old/data_numpy.py
pyslabs/old/error.py
pyslabs/old/info.py
pyslabs/old/main.py
pyslabs-0.1.7.dist-info/LICENSE
pyslabs-0.1.7.dist-info/METADATA
pyslabs-0.1.7.dist-info/WHEEL
pyslabs-0.1.7.dist-info/entry_points.txt
pyslabs-0.1.7.dist-info/top_level.txt
pyslabs-0.1.7.dist-info/RECORD
